mobt/MobException.py
mobt/MobSecrets.py
mobt/Module.py
mobt/WorkDir.py
mobt/__init__.py
mobt/di.py
mobt/Cache/CacheInterface.py
mobt/Cache/FileSystemCache.py
mobt/Cache/Module.py
mobt/Cache/__init__.py
mobt/Controllers/__init__.py
mobt/Controllers/boostrap_cli_app.py
mobt/Controllers/cli.py
mobt/Controllers/common_params.py
mobt/Controllers/done.py
mobt/Controllers/next.py
mobt/Controllers/squash.py
mobt/Controllers/start.py
mobt/Controllers/wip_commit.py
mobt/EventSystem/EventBase.py
mobt/EventSystem/EventListener.py
mobt/EventSystem/EventManager.py
mobt/EventSystem/Module.py
mobt/EventSystem/__init__.py
mobt/FileAccess/FileAccess.py
mobt/FileAccess/__init__.py
mobt/GitCli/BranchName.py
mobt/GitCli/Exceptions.py
mobt/GitCli/GitCliInterface.py
mobt/GitCli/GitCliWithAutoRollback.py
mobt/GitCli/Module.py
mobt/GitCli/__init__.py
mobt/GitCli/GitPython/GitCliWithGitPython.py
mobt/GitCli/GitPython/Module.py
mobt/GitCli/GitPython/__init__.py
mobt/GitCli/GitPython/GitActions/AddAll.py
mobt/GitCli/GitPython/GitActions/AddEntryToInfoExclude.py
mobt/GitCli/GitPython/GitActions/Checkout.py
mobt/GitCli/GitPython/GitActions/Commit.py
mobt/GitCli/GitPython/GitActions/ComposedGitActions.py
mobt/GitCli/GitPython/GitActions/CreateHead.py
mobt/GitCli/GitPython/GitActions/Exceptions.py
mobt/GitCli/GitPython/GitActions/Fetch.py
mobt/GitCli/GitPython/GitActions/GitAction.py
mobt/GitCli/GitPython/GitActions/GitActionWasExecuted.py
mobt/GitCli/GitPython/GitActions/PermanentlyCleanWorkingDirectory.py
mobt/GitCli/GitPython/GitActions/PullWithRebase.py
mobt/GitCli/GitPython/GitActions/Push.py
mobt/GitCli/GitPython/GitActions/Rebase.py
mobt/GitCli/GitPython/GitActions/Reset.py
mobt/GitCli/GitPython/GitActions/SquashAll.py
mobt/GitCli/GitPython/GitActions/StashIfDirty.py
mobt/GitCli/GitPython/GitActions/StashPop.py
mobt/GitCli/GitPython/GitActions/TryStashPop.py
mobt/GitCli/GitPython/GitActions/__init__.py
mobt/GitCli/GitPython/GitActions/shared/__init__.py
mob_tool-2.0.1.dist-info/LICENSE.txt
mob_tool-2.0.1.dist-info/METADATA
mob_tool-2.0.1.dist-info/WHEEL
mob_tool-2.0.1.dist-info/entry_points.txt
mob_tool-2.0.1.dist-info/top_level.txt
mob_tool-2.0.1.dist-info/RECORD
