Metadata-Version: 2.1
Name: mob-tool
Version: 2.0.1
Summary: Mob session management tool
Author: rfst
License: MIT License
Project-URL: source, https://github.com/stavarengo/mob-tool
Project-URL: Say_Thanks, https://saythanks.io/to/faelsta
Keywords: mob,mob-programming,timer,mob-programming-timer,cli-tool,remote-mob-programming,remote-mobs,mob-timer,mob-tool
Classifier: Development Status :: 5 - Production/Stable
Classifier: Environment :: Console
Classifier: Intended Audience :: Developers
Classifier: License :: OSI Approved :: MIT License
Classifier: Programming Language :: Python
Requires-Python: >=3.11
License-File: LICENSE.txt
Requires-Dist: click ==8.1.7
Requires-Dist: injector ==0.21.0
Requires-Dist: dataclasses-json ==0.6.7
Requires-Dist: GitPython ==3.1.43
Requires-Dist: colorama ==0.4.6
Requires-Dist: requests ==2.32.3
Requires-Dist: packaging ==23.2
Requires-Dist: marshmallow ==3.21.3
Requires-Dist: flet ==0.9.0
Requires-Dist: platformdirs ==4.2.2
Requires-Dist: setuptools ==70.1.1
